litewave_audit_lib/__init__.py
litewave_audit_lib/base.py
litewave_audit_lib/file_logger.py
litewave_audit_lib/log_factory.py
litewave_audit_lib/nats_logger.py
litewave_audit_lib-0.1.11.dist-info/METADATA
litewave_audit_lib-0.1.11.dist-info/WHEEL
litewave_audit_lib-0.1.11.dist-info/top_level.txt
litewave_audit_lib-0.1.11.dist-info/RECORD
