Metadata-Version: 2.4
Name: litewave-audit-lib
Version: 0.1.11
Summary: A lightweight audit logging library with pluggable backends
Home-page: https://github.com/aiorch/litewave-audit-lib
Author: Sonu Sudhakaran
Author-email: Sonu Sudhakaran <sonu@litewave.ai>
Requires-Python: >=3.7
Requires-Dist: nats-py>=2.0.0
Dynamic: author
Dynamic: home-page
Dynamic: requires-python
